{
  "_fetch_time": "2026-06-14T06:44:57.275894+00:00",
  "orel": {
    "name": "Орёл",
    "river": "р. Ока",
    "lat": 52.925,
    "lon": 36.025,
    "time": [
      "2026-06-07",
      "2026-06-08",
      "2026-06-09",
      "2026-06-10",
      "2026-06-11",
      "2026-06-12",
      "2026-06-13",
      "2026-06-14",
      "2026-06-15",
      "2026-06-16",
      "2026-06-17",
      "2026-06-18",
      "2026-06-19",
      "2026-06-20",
      "2026-06-21",
      "2026-06-22",
      "2026-06-23",
      "2026-06-24",
      "2026-06-25",
      "2026-06-26",
      "2026-06-27",
      "2026-06-28",
      "2026-06-29"
    ],
    "discharge": [
      14.4,
      13.4,
      12.5,
      11.8,
      11.4,
      11.1,
      11.5,
      14.9,
      15.0,
      17.6,
      17.5,
      17.7,
      16.6,
      15.4,
      14.7,
      13.9,
      13.1,
      12.4,
      15.9,
      17.7,
      18.7,
      17.7,
      16.8
    ],
    "discharge_mean": [
      14.4,
      13.4,
      12.5,
      11.8,
      11.4,
      11.1,
      11.3,
      13.0,
      13.4,
      15.3,
      15.3,
      15.4,
      15.0,
      14.7,
      14.6,
      14.4,
      14.3,
      14.2,
      14.5,
      14.8,
      15.3,
      15.5,
      15.6
    ],
    "discharge_max": [
      14.4,
      13.4,
      12.5,
      11.8,
      11.4,
      11.2,
      13.3,
      15.0,
      15.5,
      20.9,
      21.0,
      21.4,
      20.2,
      20.4,
      21.1,
      23.0,
      23.6,
      23.9,
      23.5,
      23.3,
      29.4,
      36.1,
      39.6
    ],
    "current_discharge": 14.9,
    "peak_discharge": 18.7,
    "peak_date": "2026-06-27",
    "trend_arrow": "↑↑",
    "flood_ratio": 1.07,
    "wave_arrival_serpukhov": {
      "earliest": "2026-07-02",
      "latest": "2026-07-05"
    },
    "source_status": "ok"
  },
  "mtsensk": {
    "name": "Мценск",
    "river": "р. Ока",
    "lat": 53.275,
    "lon": 36.575,
    "time": [
      "2026-06-07",
      "2026-06-08",
      "2026-06-09",
      "2026-06-10",
      "2026-06-11",
      "2026-06-12",
      "2026-06-13",
      "2026-06-14",
      "2026-06-15",
      "2026-06-16",
      "2026-06-17",
      "2026-06-18",
      "2026-06-19",
      "2026-06-20",
      "2026-06-21",
      "2026-06-22",
      "2026-06-23",
      "2026-06-24",
      "2026-06-25",
      "2026-06-26",
      "2026-06-27",
      "2026-06-28",
      "2026-06-29"
    ],
    "discharge": [
      32.4,
      30.1,
      27.8,
      25.6,
      23.5,
      21.6,
      20.1,
      19.7,
      20.9,
      22.2,
      23.3,
      24.7,
      25.0,
      24.8,
      23.9,
      23.6,
      23.3,
      22.1,
      21.5,
      23.6,
      25.8,
      24.9,
      23.7
    ],
    "discharge_mean": [
      32.4,
      30.1,
      27.8,
      25.6,
      23.5,
      21.6,
      20.0,
      19.6,
      20.8,
      22.2,
      23.6,
      24.8,
      24.7,
      24.4,
      24.1,
      24.3,
      24.5,
      24.4,
      24.2,
      24.4,
      24.9,
      25.6,
      26.4
    ],
    "discharge_max": [
      32.4,
      30.1,
      27.8,
      25.6,
      23.5,
      21.6,
      20.2,
      20.2,
      23.7,
      28.1,
      31.9,
      36.0,
      37.3,
      37.8,
      37.5,
      38.6,
      43.8,
      46.4,
      47.3,
      47.3,
      48.5,
      50.6,
      57.9
    ],
    "current_discharge": 19.7,
    "peak_discharge": 25.8,
    "peak_date": "2026-06-27",
    "trend_arrow": "→",
    "flood_ratio": 0.8,
    "wave_arrival_serpukhov": {
      "earliest": "2026-07-02",
      "latest": "2026-07-04"
    },
    "source_status": "ok"
  },
  "belev": {
    "name": "Белёв",
    "river": "р. Ока",
    "lat": 53.775,
    "lon": 36.125,
    "time": [
      "2026-06-07",
      "2026-06-08",
      "2026-06-09",
      "2026-06-10",
      "2026-06-11",
      "2026-06-12",
      "2026-06-13",
      "2026-06-14",
      "2026-06-15",
      "2026-06-16",
      "2026-06-17",
      "2026-06-18",
      "2026-06-19",
      "2026-06-20",
      "2026-06-21",
      "2026-06-22",
      "2026-06-23",
      "2026-06-24",
      "2026-06-25",
      "2026-06-26",
      "2026-06-27",
      "2026-06-28",
      "2026-06-29"
    ],
    "discharge": [
      77.3,
      72.5,
      67.4,
      62.7,
      58.7,
      55.2,
      53.0,
      55.0,
      63.0,
      66.0,
      71.6,
      72.3,
      72.0,
      69.6,
      66.6,
      64.9,
      62.7,
      59.7,
      59.5,
      68.7,
      71.8,
      70.5,
      66.8
    ],
    "discharge_mean": [
      77.3,
      72.5,
      67.4,
      62.7,
      58.7,
      55.2,
      52.7,
      54.0,
      58.6,
      61.9,
      66.9,
      68.3,
      68.2,
      67.0,
      66.2,
      66.2,
      66.1,
      65.9,
      65.8,
      66.6,
      67.9,
      69.8,
      71.3
    ],
    "discharge_max": [
      77.3,
      72.5,
      67.4,
      62.7,
      58.7,
      55.2,
      53.3,
      55.9,
      67.4,
      75.9,
      88.7,
      93.8,
      95.8,
      96.5,
      95.2,
      96.7,
      112.0,
      120.3,
      122.3,
      123.7,
      130.8,
      136.4,
      156.0
    ],
    "current_discharge": 55.0,
    "peak_discharge": 72.3,
    "peak_date": "2026-06-18",
    "trend_arrow": "→",
    "flood_ratio": 0.84,
    "wave_arrival_serpukhov": {
      "earliest": "2026-06-22",
      "latest": "2026-06-24"
    },
    "source_status": "ok"
  },
  "kaluga": {
    "name": "Калуга",
    "river": "р. Ока",
    "lat": 54.475,
    "lon": 36.275,
    "time": [],
    "discharge": [],
    "discharge_mean": [],
    "discharge_max": [],
    "current_discharge": null,
    "peak_discharge": null,
    "peak_date": null,
    "trend_arrow": "?",
    "flood_ratio": null,
    "wave_arrival_serpukhov": null,
    "source_status": "unavailable"
  },
  "aleksin": {
    "name": "Алексин",
    "river": "р. Ока",
    "lat": 54.475,
    "lon": 37.025,
    "time": [
      "2026-06-07",
      "2026-06-08",
      "2026-06-09",
      "2026-06-10",
      "2026-06-11",
      "2026-06-12",
      "2026-06-13",
      "2026-06-14",
      "2026-06-15",
      "2026-06-16",
      "2026-06-17",
      "2026-06-18",
      "2026-06-19",
      "2026-06-20",
      "2026-06-21",
      "2026-06-22",
      "2026-06-23",
      "2026-06-24",
      "2026-06-25",
      "2026-06-26",
      "2026-06-27",
      "2026-06-28",
      "2026-06-29"
    ],
    "discharge": [
      216.8,
      206.0,
      196.2,
      186.5,
      178.1,
      170.4,
      163.8,
      160.8,
      163.1,
      175.2,
      190.4,
      207.4,
      220.3,
      219.8,
      216.3,
      210.8,
      205.1,
      198.5,
      189.6,
      184.8,
      188.2,
      189.6,
      186.1
    ],
    "discharge_mean": [
      216.8,
      206.0,
      196.2,
      186.5,
      178.1,
      170.4,
      163.9,
      161.7,
      164.1,
      173.1,
      187.4,
      201.2,
      209.0,
      208.6,
      206.5,
      205.4,
      206.0,
      206.1,
      204.9,
      204.0,
      206.3,
      211.9,
      218.7
    ],
    "discharge_max": [
      216.8,
      206.0,
      196.7,
      186.9,
      178.1,
      170.4,
      165.0,
      164.2,
      173.6,
      198.5,
      241.1,
      269.4,
      281.5,
      278.9,
      287.4,
      294.1,
      353.8,
      380.1,
      392.6,
      404.5,
      422.6,
      444.7,
      449.8
    ],
    "current_discharge": 160.8,
    "peak_discharge": 220.3,
    "peak_date": "2026-06-19",
    "trend_arrow": "→",
    "flood_ratio": 0.82,
    "wave_arrival_serpukhov": {
      "earliest": "2026-06-20",
      "latest": "2026-06-22"
    },
    "source_status": "ok"
  },
  "tarusa": {
    "name": "Таруса",
    "river": "р. Ока",
    "lat": 54.725,
    "lon": 37.175,
    "time": [
      "2026-06-07",
      "2026-06-08",
      "2026-06-09",
      "2026-06-10",
      "2026-06-11",
      "2026-06-12",
      "2026-06-13",
      "2026-06-14",
      "2026-06-15",
      "2026-06-16",
      "2026-06-17",
      "2026-06-18",
      "2026-06-19",
      "2026-06-20",
      "2026-06-21",
      "2026-06-22",
      "2026-06-23",
      "2026-06-24",
      "2026-06-25",
      "2026-06-26",
      "2026-06-27",
      "2026-06-28",
      "2026-06-29"
    ],
    "discharge": [
      223.9,
      212.8,
      202.2,
      192.6,
      183.5,
      175.2,
      168.4,
      165.0,
      166.1,
      177.2,
      193.5,
      209.4,
      225.5,
      226.0,
      222.9,
      218.3,
      211.3,
      206.0,
      197.2,
      190.4,
      191.8,
      193.5,
      190.9
    ],
    "discharge_mean": [
      223.9,
      212.8,
      202.4,
      192.6,
      183.5,
      175.2,
      168.6,
      165.4,
      167.6,
      175.6,
      190.3,
      203.9,
      213.5,
      214.4,
      212.9,
      211.7,
      211.9,
      212.0,
      211.0,
      210.0,
      211.8,
      217.1,
      223.8
    ],
    "discharge_max": [
      223.9,
      212.8,
      202.7,
      192.6,
      183.5,
      175.6,
      169.2,
      169.2,
      178.1,
      200.4,
      245.0,
      275.1,
      290.1,
      286.7,
      293.4,
      303.8,
      359.6,
      393.5,
      404.5,
      418.8,
      435.5,
      457.1,
      463.5
    ],
    "current_discharge": 165.0,
    "peak_discharge": 226.0,
    "peak_date": "2026-06-20",
    "trend_arrow": "→",
    "flood_ratio": 0.82,
    "wave_arrival_serpukhov": {
      "earliest": "2026-06-20",
      "latest": "2026-06-22"
    },
    "source_status": "ok"
  },
  "kozelsk": {
    "name": "Козельск (Жиздра)",
    "river": "р. Жиздра",
    "lat": 54.025,
    "lon": 35.775,
    "time": [],
    "discharge": [],
    "discharge_mean": [],
    "discharge_max": [],
    "current_discharge": null,
    "peak_discharge": null,
    "peak_date": null,
    "trend_arrow": "?",
    "flood_ratio": null,
    "wave_arrival_serpukhov": null,
    "source_status": "unavailable"
  },
  "_status": "partial"
}